pwned/__init__.py
pwned/apps.py
pwned/client.py
pwned/settings.py
pwned/validators.py
django_pwned_validator-0.0.6.dist-info/LICENSE
django_pwned_validator-0.0.6.dist-info/WHEEL
django_pwned_validator-0.0.6.dist-info/METADATA
django_pwned_validator-0.0.6.dist-info/RECORD
