Metadata-Version: 2.1
Name: django-pwned-validator
Version: 0.0.6
Summary: A PwnedPassword validator for Django
License: MIT
Author: Craig Loftus
Author-email: craigloftus@gmail.com
Requires-Python: >=3.6
Classifier: License :: OSI Approved :: MIT License
Classifier: Programming Language :: Python :: 3
Classifier: Programming Language :: Python :: 3.6
Classifier: Programming Language :: Python :: 3.7
Classifier: Programming Language :: Python :: 3.8
Classifier: Programming Language :: Python :: 3.9
Requires-Dist: requests (>=2.25.1,<3.0.0)
